bytesfunc/__init__.py
bytesfunc/and_.cp314-win_amd64.pyd
bytesfunc/ball.cp314-win_amd64.pyd
bytesfunc/bany.cp314-win_amd64.pyd
bytesfunc/bmax.cp314-win_amd64.pyd
bytesfunc/bmin.cp314-win_amd64.pyd
bytesfunc/bsum.cp314-win_amd64.pyd
bytesfunc/eq.cp314-win_amd64.pyd
bytesfunc/findindex.cp314-win_amd64.pyd
bytesfunc/ge.cp314-win_amd64.pyd
bytesfunc/gt.cp314-win_amd64.pyd
bytesfunc/invert.cp314-win_amd64.pyd
bytesfunc/le.cp314-win_amd64.pyd
bytesfunc/lshift.cp314-win_amd64.pyd
bytesfunc/lt.cp314-win_amd64.pyd
bytesfunc/ne.cp314-win_amd64.pyd
bytesfunc/or_.cp314-win_amd64.pyd
bytesfunc/rshift.cp314-win_amd64.pyd
bytesfunc/simdsupport.cp314-win_amd64.pyd
bytesfunc/xor.cp314-win_amd64.pyd
bytesfunc-3.4.8.dist-info/licenses/LICENSE
bytesfunc-3.4.8.dist-info/METADATA
bytesfunc-3.4.8.dist-info/WHEEL
bytesfunc-3.4.8.dist-info/top_level.txt
bytesfunc-3.4.8.dist-info/RECORD
