Metadata-Version: 2.4
Name: bytesfunc
Version: 3.4.8
Summary: Fast bytes and bytearray processing functions
Home-page: https://github.com/m1griffin/bytesfunc
Author: M Griffin
Author-email: m12.griffin@gmail.com
License: Apache License V2.0
Keywords: bytes and bytearray functions
Classifier: Development Status :: 5 - Production/Stable
Classifier: Intended Audience :: Developers
Classifier: Topic :: Scientific/Engineering :: Mathematics
Classifier: License :: OSI Approved :: Apache Software License
Classifier: Programming Language :: Python :: 3.6
License-File: LICENSE
Dynamic: author
Dynamic: author-email
Dynamic: classifier
Dynamic: description
Dynamic: description-content-type
Dynamic: home-page
Dynamic: keywords
Dynamic: license
Dynamic: license-file
Dynamic: summary
